README.md
setup.py
zmq_cache_client/__init__.py
zmq_cache_client/zmq_cache.py
zmq_cache_client/zmq_client.py
zmq_cache_client/zmq_message.py
zmq_cache_client/zmq_message_types.py
zmq_cache_client.egg-info/PKG-INFO
zmq_cache_client.egg-info/SOURCES.txt
zmq_cache_client.egg-info/dependency_links.txt
zmq_cache_client.egg-info/requires.txt
zmq_cache_client.egg-info/top_level.txt