Metadata-Version: 2.1
Name: zmq-cache-client
Version: 0.0.1
Summary: ZeroMQ look aside cache Python client
Home-page: https://github.com/yunluyl/zmq_cache_client_py
Author: Yun Lu
Author-email: luyun198993@gmail.com
License: UNKNOWN
Platform: UNKNOWN
Classifier: Programming Language :: Python :: 3
Classifier: License :: OSI Approved :: MIT License
Classifier: Operating System :: OS Independent
